[{"fecha":"18-11-2021 05:44","nombre":"976139373"},{"fecha":"18-11-2021 05:45","nombre":[{"nombre":"Eduardo Gonzalez"}]},{"fecha":"18-11-2021 05:46","nombre":"juandy"},{"fecha":"18-11-2021 05:47","nombre":"Juan Guillermo"},{"fecha":"18-11-2021 05:47","nombre":"IJLR"},{"fecha":"18-11-2021 05:47","nombre":"Rodrigo Molina"},{"fecha":"18-11-2021 05:48","nombre":"IJLR"},{"fecha":"18-11-2021 05:48","nombre":"Roko"},{"fecha":"18-11-2021 05:49","nombre":"Fernando Anaya"},{"fecha":"18-11-2021 05:49","nombre":"Fernando Anaya"},{"fecha":"18-11-2021 05:49","nombre":"IJLR"},{"fecha":"18-11-2021 05:51","nombre":"Tomy Ponce Santos"},{"fecha":"18-11-2021 05:54","nombre":"Eduardo Gonzalez"},{"fecha":"18-11-2021 05:55","nombre":"IJLR"},{"fecha":"18-11-2021 05:56","nombre":"IJLR"},{"fecha":"18-11-2021 05:59","nombre":"Ericson"},{"fecha":"18-11-2021 05:59","nombre":"Ericson"},{"fecha":"18-11-2021 06:02","nombre":"A."},{"fecha":"18-11-2021 06:04","nombre":"Chiquinquirá  Gómez"},{"fecha":"18-11-2021 06:04","nombre":"Chiquinquirá  Gómez"},{"fecha":"18-11-2021 06:04","nombre":"Tomy Ponce Santos"},{"fecha":"18-11-2021 06:04","nombre":"Manuel Gutierrez"},{"fecha":"18-11-2021 06:07","nombre":"IJLR"},{"fecha":"18-11-2021 06:07","nombre":"Ricardo Montero"},{"fecha":"18-11-2021 06:07","nombre":"ADOLF MENKE"},{"fecha":"18-11-2021 06:08","nombre":"IJLR"},{"fecha":"18-11-2021 06:09","nombre":"Patricio Alarcón"},{"fecha":"18-11-2021 06:10","nombre":"IJLR"},{"fecha":"18-11-2021 06:10","nombre":"Chiquinquirá  Gómez"},{"fecha":"18-11-2021 06:14","nombre":"Patricio Alarcón","numero":"941376829"},{"fecha":"18-11-2021 06:14","nombre":"Patricio Alarcón","numero":"941376829"},{"fecha":"18-11-2021 06:15","nombre":"Patricio Alarcón","numero":"941376829"},{"fecha":"18-11-2021 06:15","nombre":"Sweet Josefina","numero":"948086786"},{"fecha":"18-11-2021 06:15","nombre":"Alfredo Aichele","numero":"993973848"},{"fecha":"18-11-2021 06:16","nombre":"Cami Lafertt","numero":"997879649"},{"fecha":"18-11-2021 06:16","nombre":"Cami Lafertt","numero":"997879649"},{"fecha":"18-11-2021 06:16","nombre":"Cami Lafertt","numero":"997879649"},{"fecha":"18-11-2021 06:17","nombre":"Ericson","numero":"999824052"},{"fecha":"18-11-2021 06:17","nombre":"Ericson","numero":"999824052"},{"fecha":"18-11-2021 06:18","nombre":"Roko","numero":"976139373"},{"fecha":"18-11-2021 06:20","nombre":"IJLR","numero":"962309622"},{"fecha":"18-11-2021 06:24","nombre":"Carlos Eduardo Santibañez","numero":"945724020"},{"fecha":"18-11-2021 06:27","nombre":"A.","numero":"962710666"},{"fecha":"18-11-2021 06:27","nombre":"IJLR","numero":"962309622"},{"fecha":"18-11-2021 06:30","nombre":"Ignacioi Bernet","numero":"978351660"},{"fecha":"18-11-2021 06:32","nombre":"IJLR","numero":"962309622"},{"fecha":"18-11-2021 06:32","nombre":"Emilio","numero":"974020403"},{"fecha":"18-11-2021 06:33","nombre":"Cristian","numero":"974791652"},{"fecha":"18-11-2021 06:33","nombre":"Cristian","numero":"974791652"},{"fecha":"18-11-2021 06:34","nombre":"Cristian","numero":"974791652"},{"fecha":"18-11-2021 06:34","nombre":"Alexander Carrero","numero":"985693258"},{"fecha":"18-11-2021 06:35","nombre":"Alfredo Aichele","numero":"993973848"},{"fecha":"18-11-2021 06:37","nombre":"Johnny","numero":"993954459"},{"fecha":"18-11-2021 06:37","nombre":"Pablo","numero":"946161724"},{"fecha":"18-11-2021 06:38","nombre":"David Silva","numero":"953741290"},{"fecha":"18-11-2021 06:39","nombre":"David Silva","numero":"953741290"},{"fecha":"18-11-2021 06:39","nombre":"IJLR","numero":"962309622"},{"fecha":"18-11-2021 06:39","nombre":"David Silva","numero":"953741290"},{"fecha":"18-11-2021 06:40","nombre":"IJLR","numero":"962309622"},{"fecha":"18-11-2021 06:40","nombre":"Roko","numero":"976139373"},{"fecha":"18-11-2021 06:40","nombre":"Eduardo Gonzalez","numero":"922532476"},{"fecha":"18-11-2021 06:41","nombre":"IJLR","numero":"962309622"},{"fecha":"18-11-2021 06:41","nombre":"Ericson","numero":"999824052"},{"fecha":"18-11-2021 06:42","nombre":"Roko","numero":"976139373"},{"fecha":"18-11-2021 06:42","nombre":"Gabbo","numero":"959490349"},{"fecha":"18-11-2021 06:43","nombre":"Ericson","numero":"999824052"},{"fecha":"18-11-2021 06:43","nombre":"Ericson","numero":"999824052"},{"fecha":"18-11-2021 06:43","nombre":"Ericson","numero":"999824052"},{"fecha":"18-11-2021 06:45","nombre":"IJLR","numero":"962309622"},{"fecha":"18-11-2021 06:49","nombre":"Alfredo Aichele","numero":"993973848"},{"fecha":"18-11-2021 06:50","nombre":"A.","numero":"962710666"},{"fecha":"18-11-2021 06:51","nombre":"Patricio Rioseco","numero":"930743929"},{"fecha":"18-11-2021 06:52","nombre":"IJLR","numero":"962309622"},{"fecha":"18-11-2021 06:53","nombre":"Patricio Rioseco","numero":"930743929"},{"fecha":"18-11-2021 06:54","nombre":"Juan Sanhueza Faúndez","numero":"974213446"},{"fecha":"18-11-2021 06:55","nombre":"Ericson","numero":"999824052"},{"fecha":"18-11-2021 06:55","nombre":"Cami Lafertt","numero":"997879649"},{"fecha":"18-11-2021 06:55","nombre":"Alejandro Islas","numero":"938830913"},{"fecha":"18-11-2021 06:56","nombre":"IJLR","numero":"962309622"},{"fecha":"18-11-2021 06:57","nombre":"Roko","numero":"976139373"},{"fecha":"18-11-2021 06:58","nombre":"Eduardo Gonzalez","numero":"922532476"},{"fecha":"18-11-2021 06:59","nombre":"IJLR","numero":"962309622"},{"fecha":"18-11-2021 07:00","nombre":"Santiago","numero":"920762491"},{"fecha":"18-11-2021 07:00","nombre":"Santiago","numero":"920762491"},{"fecha":"18-11-2021 07:00","nombre":"IJLR","numero":"962309622"},{"fecha":"18-11-2021 07:00","nombre":"FECF","numero":"974565630"},{"fecha":"18-11-2021 07:00","nombre":"Christian Acuña M.","numero":"994988343"},{"fecha":"18-11-2021 07:03","nombre":"IJLR","numero":"962309622"},{"fecha":"18-11-2021 07:04","nombre":"IJLR","numero":"962309622"},{"fecha":"18-11-2021 07:05","nombre":"Juan Sanhueza Faúndez","numero":"974213446"},{"fecha":"18-11-2021 07:05","nombre":"IJLR","numero":"962309622"},{"fecha":"18-11-2021 07:06","nombre":"Marcel","numero":"934823948"},{"fecha":"18-11-2021 07:06","nombre":"Gabbo","numero":"959490349"},{"fecha":"18-11-2021 07:07","nombre":"Marcel","numero":"934823948"},{"fecha":"18-11-2021 07:07","nombre":"Marcel","numero":"934823948"},{"fecha":"18-11-2021 07:12","nombre":"Luis  Vásquez Quev","numero":"996947907"},{"fecha":"18-11-2021 07:15","nombre":"Christian Acuña M.","numero":"994988343"},{"fecha":"18-11-2021 07:16","nombre":"Santiago","numero":"920762491"},{"fecha":"18-11-2021 07:16","nombre":"JECO","numero":"954161790"},{"fecha":"18-11-2021 07:16","nombre":"Santiago","numero":"920762491"},{"fecha":"18-11-2021 07:17","nombre":"Santiago","numero":"920762491"},{"fecha":"18-11-2021 07:19","nombre":"IJLR","numero":"962309622"},{"fecha":"18-11-2021 07:20","nombre":"Alejandro Islas","numero":"938830913"},{"fecha":"18-11-2021 07:21","nombre":"Ericson","numero":"999824052"},{"fecha":"18-11-2021 07:21","nombre":"Ericson","numero":"999824052"},{"fecha":"18-11-2021 07:22","nombre":"IJLR","numero":"962309622"},{"fecha":"18-11-2021 07:23","nombre":"Cako Palma","numero":"963537302"},{"fecha":"18-11-2021 07:23","nombre":"IJLR","numero":"962309622"},{"fecha":"18-11-2021 07:24","nombre":"Carlos Eduardo Santibañez","numero":"945724020"},{"fecha":"18-11-2021 07:24","nombre":"Carlos Eduardo Santibañez","numero":"945724020"},{"fecha":"18-11-2021 07:24","nombre":"Brad Castillo~","numero":"946905378"},{"fecha":"18-11-2021 07:24","nombre":"IJLR","numero":"962309622"},{"fecha":"18-11-2021 07:25","nombre":"IJLR","numero":"962309622"},{"fecha":"18-11-2021 07:26","nombre":"IJLR","numero":"962309622"},{"fecha":"18-11-2021 07:27","nombre":"IJLR","numero":"962309622"},{"fecha":"18-11-2021 07:27","nombre":"German Rojas","numero":"981245537"},{"fecha":"18-11-2021 07:31","nombre":"Eduardo Gonzalez","numero":"922532476"},{"fecha":"18-11-2021 07:32","nombre":"Christian Acuña M.","numero":"994988343"},{"fecha":"18-11-2021 07:32","nombre":"Chiquinquirá  Gómez","numero":"936706570"},{"fecha":"18-11-2021 07:32","nombre":"Chiquinquirá  Gómez","numero":"936706570"},{"fecha":"18-11-2021 07:35","nombre":"Carmen Gloria Sandoval","numero":"978589601"},{"fecha":"18-11-2021 07:36","nombre":"IJLR","numero":"962309622"},{"fecha":"18-11-2021 07:38","nombre":"Alexander Carrero","numero":"985693258"},{"fecha":"18-11-2021 07:39","nombre":"ADOLF MENKE","numero":"994170514"},{"fecha":"18-11-2021 07:39","nombre":"Ericson","numero":"999824052"},{"fecha":"18-11-2021 07:39","nombre":"Ericson","numero":"999824052"},{"fecha":"18-11-2021 07:39","nombre":"Ericson","numero":"999824052"},{"fecha":"18-11-2021 07:39","nombre":"Ericson","numero":"999824052"},{"fecha":"18-11-2021 07:39","nombre":"Alejandro Islas","numero":"938830913"},{"fecha":"18-11-2021 07:40","nombre":"IJLR","numero":"962309622"},{"fecha":"18-11-2021 07:41","nombre":"Carlos Eduardo Santibañez","numero":"945724020"},{"fecha":"18-11-2021 07:41","nombre":"Carlos Eduardo Santibañez","numero":"945724020"},{"fecha":"18-11-2021 07:41","nombre":"IJLR","numero":"962309622"},{"fecha":"18-11-2021 07:42","nombre":"Juan Sanhueza Faúndez","numero":"974213446"},{"fecha":"18-11-2021 07:43","nombre":"IJLR","numero":"962309622"},{"fecha":"18-11-2021 07:43","nombre":"FECF","numero":"974565630"},{"fecha":"18-11-2021 07:43","nombre":"IJLR","numero":"962309622"}]